Workbook

Sheet Inputs
A1: FX HEDGING MODEL — EUR/USD Receivable
A2: Aerospace Manufacturer | Stage 2 Excel Prototype | All yellow cells are editable inputs
A4: CORE SCENARIO ASSUMPTIONS
A5: FC_AMT | B5: EUR Receivable Amount (€) | C5: 20000000 | D5: Notional EUR to be received at settlement
A6: S0_in | B6: Spot Rate Today (USD/EUR) | C6: 1.093 | D6: Source: Reuters FX, Apr 14 2026
A7: F0_in | B7: Forward Rate (USD/EUR) | C7: 1.093 | D7: 6-month outright forward quote
A8: R_USD | B8: USD Interest Rate (ann.) | C8: 0.0525 | D8: SOFR + spread, annualised
A9: R_FC | B9: EUR Interest Rate (ann.) | C9: 0.0385 | D9: €STR + spread, annualised
A10: T_DAYS | B10: Days to Settlement | C10: 180 | D10: Approximate settlement horizon
A12: OPTION PARAMETERS
A13: K_PUT | B13: Put Strike (USD/EUR) | C13: 1.07 | D13: Out-of-the-money put, ~2% below spot
A14: K_CALL | B14: Call Strike (USD/EUR) | C14: 1.12 | D14: Out-of-the-money call for collar
A15: PREM_PUT | B15: Put Premium (USD per EUR) | C15: 0.0085 | D15: ~0.78% of notional; market indicative
A16: PREM_CALL | B16: Call Premium (USD per EUR) | C16: 0.0085 | D16: ~0.78% of notional; set equal for ZCC
A18: DERIVED CHECKS (auto-calculated)
A19: Base USD Proceeds (forward) | B19: =C7*C5 -> 21860000
A20: MM Forward (parity check) | B20: =C6*(1+C8)^(C10/360)/(1+C9)^(C10/360) -> 1.1003427
A21: Forward vs MM diff (bps) | B21: =(C7-B20)*10000 -> -73.426929
A22: Put cost total (USD) | B22: =C15*C5 -> 170000
A23: Call premium total (USD) | B23: =C16*C5 -> 170000
A24: Net collar premium (USD) | B24: =(C15-C16)*C5 -> 0

Sheet Forward_MM
A1: FORWARD CONTRACT & MONEY MARKET HEDGE
A2: The Forward locks in the rate today. The Money Market Hedge replicates it by borrowing EUR, converting at spot, and investing USD. Interest-rate parity implies Forward ≈ MM result.
A4: A. FORWARD CONTRACT HEDGE
A5: Parameter | B5: Value | C5: Format
A6: EUR Notional | B6: =Inputs!C5 -> 20000000 | C6: FC_AMT pulled from Inputs
A7: Forward Rate locked | B7: =Inputs!C7 -> 1.093 | C7: F0_in from Inputs
A8: USD Proceeds (locked) | B8: =B6*B7 -> 21860000 | C8: Fully hedged receipt
A9: Days to Settlement | B9: =Inputs!C10 -> 180 | C9: T_DAYS
A10: ⟹ Net USD received at settlement (forward) | D10: =B8 -> 21860000
A12: B. MONEY MARKET HEDGE (replication)
A13: Step | B13: Description | C13: Amount (USD/EUR)
A14: Step 1 | B14: PV of EUR receivable (borrow this amt in EUR today) | C14: =Inputs!C5/(1+Inputs!C9)^(Inputs!C10/360) -> 19625772
A15: Step 2 | B15: Convert EUR to USD at spot rate | C15: =C14*Inputs!C6 -> 21450969
A16: Step 3 | B16: Invest USD for T days at R_USD | C16: =C15*(1+Inputs!C8)^(Inputs!C10/360) -> 22006854
A17: → Implied MM Forward Rate | B17: USD proceeds / FC_AMT (implied fwd) | C17: =C16/Inputs!C5 -> 1.1003427
A18: ⟹ Net USD received (MM replication) | D18: =C16 -> 22006854
A20: C. INTEREST RATE PARITY CHECK
A21: Forward Rate (bank quote) | B21: =Inputs!C7 -> 1.093
A22: MM Implied Forward Rate | B22: =C17 -> 1.1003427
A23: Difference (bps) | B23: =(B21-B22)*10000 -> -73.426929
A24: Parity Check | B24: =IF(ABS(B21-B22)<0.0005,"Holds (< 5 bps)","Divergence - review") -> Divergence - review

Sheet Option_Hedges
A1: OPTION HEDGES — Put, Call & Zero-Cost Collar
A2: Payoffs calculated at a user-supplied settlement spot rate S_T. Change S_T in cell C5 to see how each strategy performs. Premium costs are deducted to show net USD proceeds.
A4: SETTLEMENT SPOT RATE (S_T) — change this cell to stress-test
A5: S_T — Settlement EUR/USD spot | C5: 1.093 | D5: ← Change to see payoff impact
A7: A. LONG PUT (buy downside protection)
A8: Item | B8: Formula / Logic | C8: Value
A9: EUR Notional | C9: =Inputs!C5 -> 20000000
A10: Put Strike K_PUT | C10: =Inputs!C13 -> 1.07
A11: Settlement Spot S_T | C11: =C5 -> 1.093
A12: Put Payoff (per EUR) | C12: =MAX(C10-C11,0) -> 0
A13: Total Put Payoff (USD) | C13: =C12*C9 -> 0
A14: Put Premium Paid (USD) | C14: =Inputs!C15*Inputs!C5 -> 170000
A15: Spot Conversion (USD) | C15: =C11*C9 -> 21860000
A16: Net USD Proceeds | C16: =C15+C13-C14 -> 21690000
A17: ⟹ Net USD received (long put hedge) | C17: =C16 -> 21690000
A19: B. ZERO-COST COLLAR (long put + short call)
A20: Item | B20: Formula / Logic | C20: Value
A21: EUR Notional | C21: =Inputs!C5 -> 20000000
A22: Put Strike K_PUT | C22: =Inputs!C13 -> 1.07
A23: Call Strike K_CALL | C23: =Inputs!C14 -> 1.12
A24: Settlement Spot S_T | C24: =C5 -> 1.093
A25: Put Payoff (per EUR) | C25: =MAX(C22-C24,0) -> 0
A26: Call Liability (per EUR) | C26: =MAX(C24-C23,0) -> 0
A27: Net Option Payoff (USD) | C27: =(C25-C26)*C21 -> 0
A28: Spot Conversion (USD) | C28: =C24*C21 -> 21860000
A29: Net Collar Premium (USD) | C29: =(Inputs!C15-Inputs!C16)*Inputs!C5 -> 0
A30: Net USD Proceeds | C30: =C28+C27-C29 -> 21860000
A31: ⟹ Net USD received (zero-cost collar) | C31: =C30 -> 21860000

Sheet Sensitivity_Table
A1: SENSITIVITY TABLE — S_T from 0.95×S₀ to 1.05×S₀ (1% steps)
A2: All four hedging outcomes compared side-by-side as EUR/USD settlement rate varies. Conditional formatting highlights which strategy dominates at each rate.
A4: S_T (EUR/USD) | B4: Unhedged (USD) | C4: Forward (USD) | D4: Long Put (USD) | E4: Collar (USD) | F4: Best Strategy | G4: vs Forward ($)
A5: =Inputs!C5*(1+-0.05) -> 19000000 | B5: =A5*Inputs!C5 -> 380000000000000 | C5: =Inputs!C6*Inputs!C5 -> 21860000 | D5: =A5*Inputs!C5+MAX(Inputs!C13-A5,0)*Inputs!C5-Inputs!C15*Inputs!C5 -> 379999999830000 | E5: =A5*Inputs!C5+MAX(Inputs!C13-A5,0)*Inputs!C5-MAX(A5-Inputs!C14,0)*Inputs!C5-(Inputs!C15-Inputs!C16)*Inputs!C5 -> 22400000 | F5: =IF(AND(B5>=C5,B5>=D5,B5>=E5),"Unhedged",IF(AND(C5>=B5,C5>=D5,C5>=E5),"Forward",IF(D5>=E5,"Long Put","Collar"))) -> Unhedged | G5: =D5-C5 -> 379999977970000
A6: =Inputs!C5*(1+-0.04) -> 19200000 | B6: =A6*Inputs!C5 -> 384000000000000 | C6: =Inputs!C6*Inputs!C5 -> 21860000 | D6: =A6*Inputs!C5+MAX(Inputs!C13-A6,0)*Inputs!C5-Inputs!C15*Inputs!C5 -> 383999999830000 | E6: =A6*Inputs!C5+MAX(Inputs!C13-A6,0)*Inputs!C5-MAX(A6-Inputs!C14,0)*Inputs!C5-(Inputs!C15-Inputs!C16)*Inputs!C5 -> 22400000 | F6: =IF(AND(B6>=C6,B6>=D6,B6>=E6),"Unhedged",IF(AND(C6>=B6,C6>=D6,C6>=E6),"Forward",IF(D6>=E6,"Long Put","Collar"))) -> Unhedged | G6: =D6-C6 -> 383999977970000
A7: =Inputs!C5*(1+-0.03) -> 19400000 | B7: =A7*Inputs!C5 -> 388000000000000 | C7: =Inputs!C6*Inputs!C5 -> 21860000 | D7: =A7*Inputs!C5+MAX(Inputs!C13-A7,0)*Inputs!C5-Inputs!C15*Inputs!C5 -> 387999999830000 | E7: =A7*Inputs!C5+MAX(Inputs!C13-A7,0)*Inputs!C5-MAX(A7-Inputs!C14,0)*Inputs!C5-(Inputs!C15-Inputs!C16)*Inputs!C5 -> 22400000 | F7: =IF(AND(B7>=C7,B7>=D7,B7>=E7),"Unhedged",IF(AND(C7>=B7,C7>=D7,C7>=E7),"Forward",IF(D7>=E7,"Long Put","Collar"))) -> Unhedged | G7: =D7-C7 -> 387999977970000
A8: =Inputs!C5*(1+-0.02) -> 19600000 | B8: =A8*Inputs!C5 -> 392000000000000 | C8: =Inputs!C6*Inputs!C5 -> 21860000 | D8: =A8*Inputs!C5+MAX(Inputs!C13-A8,0)*Inputs!C5-Inputs!C15*Inputs!C5 -> 391999999830000 | E8: =A8*Inputs!C5+MAX(Inputs!C13-A8,0)*Inputs!C5-MAX(A8-Inputs!C14,0)*Inputs!C5-(Inputs!C15-Inputs!C16)*Inputs!C5 -> 22400000 | F8: =IF(AND(B8>=C8,B8>=D8,B8>=E8),"Unhedged",IF(AND(C8>=B8,C8>=D8,C8>=E8),"Forward",IF(D8>=E8,"Long Put","Collar"))) -> Unhedged | G8: =D8-C8 -> 391999977970000
A9: =Inputs!C5*(1+-0.01) -> 19800000 | B9: =A9*Inputs!C5 -> 396000000000000 | C9: =Inputs!C6*Inputs!C5 -> 21860000 | D9: =A9*Inputs!C5+MAX(Inputs!C13-A9,0)*Inputs!C5-Inputs!C15*Inputs!C5 -> 395999999830000 | E9: =A9*Inputs!C5+MAX(Inputs!C13-A9,0)*Inputs!C5-MAX(A9-Inputs!C14,0)*Inputs!C5-(Inputs!C15-Inputs!C16)*Inputs!C5 -> 22400000 | F9: =IF(AND(B9>=C9,B9>=D9,B9>=E9),"Unhedged",IF(AND(C9>=B9,C9>=D9,C9>=E9),"Forward",IF(D9>=E9,"Long Put","Collar"))) -> Unhedged | G9: =D9-C9 -> 395999977970000
A10: =Inputs!C5*(1+0) -> 20000000 | B10: =A10*Inputs!C5 -> 400000000000000 | C10: =Inputs!C6*Inputs!C5 -> 21860000 | D10: =A10*Inputs!C5+MAX(Inputs!C13-A10,0)*Inputs!C5-Inputs!C15*Inputs!C5 -> 399999999830000 | E10: =A10*Inputs!C5+MAX(Inputs!C13-A10,0)*Inputs!C5-MAX(A10-Inputs!C14,0)*Inputs!C5-(Inputs!C15-Inputs!C16)*Inputs!C5 -> 22400000 | F10: =IF(AND(B10>=C10,B10>=D10,B10>=E10),"Unhedged",IF(AND(C10>=B10,C10>=D10,C10>=E10),"Forward",IF(D10>=E10,"Long Put","Collar"))) -> Unhedged | G10: =D10-C10 -> 399999977970000
A11: =Inputs!C5*(1+0.01) -> 20200000 | B11: =A11*Inputs!C5 -> 404000000000000 | C11: =Inputs!C6*Inputs!C5 -> 21860000 | D11: =A11*Inputs!C5+MAX(Inputs!C13-A11,0)*Inputs!C5-Inputs!C15*Inputs!C5 -> 403999999830000 | E11: =A11*Inputs!C5+MAX(Inputs!C13-A11,0)*Inputs!C5-MAX(A11-Inputs!C14,0)*Inputs!C5-(Inputs!C15-Inputs!C16)*Inputs!C5 -> 22400000 | F11: =IF(AND(B11>=C11,B11>=D11,B11>=E11),"Unhedged",IF(AND(C11>=B11,C11>=D11,C11>=E11),"Forward",IF(D11>=E11,"Long Put","Collar"))) -> Unhedged | G11: =D11-C11 -> 403999977970000
A12: =Inputs!C5*(1+0.02) -> 20400000 | B12: =A12*Inputs!C5 -> 408000000000000 | C12: =Inputs!C6*Inputs!C5 -> 21860000 | D12: =A12*Inputs!C5+MAX(Inputs!C13-A12,0)*Inputs!C5-Inputs!C15*Inputs!C5 -> 407999999830000 | E12: =A12*Inputs!C5+MAX(Inputs!C13-A12,0)*Inputs!C5-MAX(A12-Inputs!C14,0)*Inputs!C5-(Inputs!C15-Inputs!C16)*Inputs!C5 -> 22400000 | F12: =IF(AND(B12>=C12,B12>=D12,B12>=E12),"Unhedged",IF(AND(C12>=B12,C12>=D12,C12>=E12),"Forward",IF(D12>=E12,"Long Put","Collar"))) -> Unhedged | G12: =D12-C12 -> 407999977970000
A13: =Inputs!C5*(1+0.03) -> 20600000 | B13: =A13*Inputs!C5 -> 412000000000000 | C13: =Inputs!C6*Inputs!C5 -> 21860000 | D13: =A13*Inputs!C5+MAX(Inputs!C13-A13,0)*Inputs!C5-Inputs!C15*Inputs!C5 -> 411999999830000 | E13: =A13*Inputs!C5+MAX(Inputs!C13-A13,0)*Inputs!C5-MAX(A13-Inputs!C14,0)*Inputs!C5-(Inputs!C15-Inputs!C16)*Inputs!C5 -> 22400000 | F13: =IF(AND(B13>=C13,B13>=D13,B13>=E13),"Unhedged",IF(AND(C13>=B13,C13>=D13,C13>=E13),"Forward",IF(D13>=E13,"Long Put","Collar"))) -> Unhedged | G13: =D13-C13 -> 411999977970000
A14: =Inputs!C5*(1+0.04) -> 20800000 | B14: =A14*Inputs!C5 -> 416000000000000 | C14: =Inputs!C6*Inputs!C5 -> 21860000 | D14: =A14*Inputs!C5+MAX(Inputs!C13-A14,0)*Inputs!C5-Inputs!C15*Inputs!C5 -> 415999999830000 | E14: =A14*Inputs!C5+MAX(Inputs!C13-A14,0)*Inputs!C5-MAX(A14-Inputs!C14,0)*Inputs!C5-(Inputs!C15-Inputs!C16)*Inputs!C5 -> 22400000 | F14: =IF(AND(B14>=C14,B14>=D14,B14>=E14),"Unhedged",IF(AND(C14>=B14,C14>=D14,C14>=E14),"Forward",IF(D14>=E14,"Long Put","Collar"))) -> Unhedged | G14: =D14-C14 -> 415999977970000
A15: =Inputs!C5*(1+0.05) -> 21000000 | B15: =A15*Inputs!C5 -> 420000000000000 | C15: =Inputs!C6*Inputs!C5 -> 21860000 | D15: =A15*Inputs!C5+MAX(Inputs!C13-A15,0)*Inputs!C5-Inputs!C15*Inputs!C5 -> 419999999830000 | E15: =A15*Inputs!C5+MAX(Inputs!C13-A15,0)*Inputs!C5-MAX(A15-Inputs!C14,0)*Inputs!C5-(Inputs!C15-Inputs!C16)*Inputs!C5 -> 22400000 | F15: =IF(AND(B15>=C15,B15>=D15,B15>=E15),"Unhedged",IF(AND(C15>=B15,C15>=D15,C15>=E15),"Forward",IF(D15>=E15,"Long Put","Collar"))) -> Unhedged | G15: =D15-C15 -> 419999977970000

Sheet Summary
A1: HEDGE STRATEGY COMPARISON — SUMMARY DASHBOARD
A2: Scenario: €20M EUR/USD receivable | Forward rate: 1.0930 | Settlement: ~180 days
A4: STRATEGY OUTCOMES AT CURRENT FORWARD RATE
A5: Strategy | B5: Gross USD | C5: Cost / Premium | D5: Net USD Proceeds | E5: vs Unhedged | F5: Key Trade-off
A6: Unhedged | B6: =Inputs!C7*Inputs!C5 -> 21860000 | C6: — | D6: =Inputs!C7*Inputs!C5 -> 21860000 | E6: =D6-D6 -> 0 | F6: Full P&L exposure to EUR/USD vol
A7: Forward Contract | B7: =Inputs!C7*Inputs!C5 -> 21860000 | C7: None | D7: =Inputs!C7*Inputs!C5 -> 21860000 | E7: =D7-D6 -> 0 | F7: Certainty, no upside participation
A8: Long Put Option | B8: =Inputs!C7*Inputs!C5 -> 21860000 | C8: =(Inputs!C15*Inputs!C5) -> 170000 | D8: =B8-C8 -> 21690000 | E8: =D8-D6 -> -170000 | F8: Floor set; upside open; premium cost
A9: Zero-Cost Collar | B9: =Inputs!C7*Inputs!C5 -> 21860000 | C9: =(Inputs!C15-Inputs!C16)*Inputs!C5 -> 0 | D9: =B9-C9 -> 21860000 | E9: =D9-D6 -> 0 | F9: No premium; upside capped at K_CALL
A11: KEY RISK METRICS
A12: 1-cent EUR/USD move → P&L impact | B12: =Inputs!C5*0.01 -> 200000
A13: 10-cent move (typical 6m range) | B13: =Inputs!C5*0.1 -> 2000000
A14: Forward breakeven vs unhedged | B14: =Inputs!C7 -> 1.093
A15: Put effective floor (after premium) | B15: =(Inputs!C13*Inputs!C5 - Inputs!C15*Inputs!C5)/Inputs!C5 -> 1.0615
A16: Collar floor | B16: =Inputs!C13 -> 1.07
A17: Collar cap | B17: =Inputs!C14 -> 1.12
